{"cameraMode":{"drawMode":0,"name":"Shaded","section":"Shading Mode"},"sceneLighting":true,"audioPlay":false,"sceneViewState":{"m_AlwaysRefresh":false,"showFog":true,"showSkybox":false,"showFlares":true,"showImageEffects":true,"showParticleSystems":true,"showVisualEffectGraphs":true,"m_FxEnabled":true},"in2DMode":false,"pivot":{"x":0.0,"y":0.005049943923950195,"z":0.0},"rotation":{"x":-0.2239765077829361,"y":0.0511363260447979,"z":-0.011768877506256104,"w":-0.9731811285018921},"size":3.6923012733459474,"orthographic":false}